pydata/__init__.py
pydata/command.py
pydata/list.py
pydata-1.0.0.dist-info/DESCRIPTION.rst
pydata-1.0.0.dist-info/METADATA
pydata-1.0.0.dist-info/RECORD
pydata-1.0.0.dist-info/WHEEL
pydata-1.0.0.dist-info/entry_points.txt
pydata-1.0.0.dist-info/metadata.json
pydata-1.0.0.dist-info/top_level.txt
tests/__init__.py
tests/test_list.py
