Metadata-Version: 2.0
Name: pydata
Version: 1.0.0
Summary: PyData Location List
Home-page: https://github.com/takezyou/pydata
Author: takezyou
Author-email: kaitokun07@icloud.com
License: MIT
Keywords: pydata
Platform: UNKNOWN
Classifier: License :: OSI Approved :: MIT License
Classifier: Programming Language :: Python :: 3.5
Classifier: Programming Language :: Python :: 3.6
Requires-Dist: beautifulsoup4
Requires-Dist: lxml
